supextend/__init__.py
supextend/app.py
supextend/config.py
supextend/cli/__init__.py
supextend/cli/entrypoint.py
supextend/cli/waitress_server.py
supextend/core/__init__.py
supextend/core/connection.py
supextend/core/resource.py
supextend/exceptions/__init__.py
supextend/exceptions/errors.py
supextend/initialization/__init__.py
supextend/loggers/__init__.py
supextend/loggers/config.py
supextend/migrations/__init__.py
supextend/migrations/env.py
supextend/migrations/versions/9881d330df53_initial_migration.py
supextend/migrations/versions/__init__.py
supextend/models/__init__.py
supextend/models/airflow_task_instances.py
supextend/models/charts.py
supextend/models/dashboards.py
supextend/models/owners.py
supextend/models/tags.py
supextend/models/workspaces.py
supextend/resources/__init__.py
supextend/resources/common/__init__.py
supextend/resources/common/superset_batch_cleaner/__init__.py
supextend/resources/common/superset_batch_cleaner/airflow_task_instance.py
supextend/resources/common/superset_batch_cleaner/chart.py
supextend/resources/common/superset_batch_cleaner/dashboard.py
supextend/resources/common/superset_batch_cleaner/owner.py
supextend/resources/common/superset_batch_cleaner/tag.py
supextend/resources/common/workspace_extension/__init__.py
supextend/resources/common/workspace_extension/workspace.py
supextend/resources/external/__init__.py
supextend/resources/external/superset/__init__.py
supextend/resources/external/superset/chart.py
supextend/resources/external/superset/dashboard.py
supextend/resources/external/superset/main.py
supextend/resources/internal/__init__.py
supextend/resources/internal/superset_batch_cleaner/__init__.py
supextend/resources/internal/superset_batch_cleaner/airflow_entrypoint.py
supextend/resources/internal/superset_batch_cleaner/airflow_task_instance.py
supextend/resources/internal/superset_batch_cleaner/chart.py
supextend/resources/internal/superset_batch_cleaner/dashboard.py
superset_extender-0.11.0.dist-info/LICENSE.txt
superset_extender-0.11.0.dist-info/METADATA
superset_extender-0.11.0.dist-info/WHEEL
superset_extender-0.11.0.dist-info/entry_points.txt
superset_extender-0.11.0.dist-info/top_level.txt
superset_extender-0.11.0.dist-info/RECORD
