Metadata-Version: 2.1
Name: superset-extender
Version: 0.11.0
Summary: An Apache-Superset extension app that enhances it with tagging, workspaces, batch cleaning
Home-page: https://gitlab.com/rework-space.com/apache-superset/superset-extender
Author: Rework-space
License: Apache License, Version 2.0
Project-URL: Bug Tracker, https://gitlab.com/rework-space.com/apache-superset/superset-extender/-/issues
Classifier: Programming Language :: Python :: 3
Classifier: Operating System :: OS Independent
Requires-Python: >=3.6
License-File: LICENSE.txt
Requires-Dist: python-dotenv
Requires-Dist: flask
Requires-Dist: flask-sqlalchemy
Requires-Dist: requests
Requires-Dist: python-dateutil
Requires-Dist: flask-wtf
Requires-Dist: loguru
Requires-Dist: prettytable
Requires-Dist: pdoc3
Requires-Dist: flask-bcrypt
Requires-Dist: flask-login
Requires-Dist: psycopg2-binary
Requires-Dist: flask-oidc
Requires-Dist: flask-migrate
Requires-Dist: waitress
Requires-Dist: itsdangerous (==2.0.1)
Requires-Dist: sphinx
Requires-Dist: sphinx-tabs
Requires-Dist: karma-sphinx-theme
Requires-Dist: build
Requires-Dist: twine
Requires-Dist: importlib-metadata ; python_version < "3.10"
